osm_export_tool/__init__.py
osm_export_tool/cmd.py
osm_export_tool/geometry.py
osm_export_tool/mapping.py
osm_export_tool/nontabular.py
osm_export_tool/package.py
osm_export_tool/sources.py
osm_export_tool/sql.py
osm_export_tool/tabular.py
osm_export_tool/mappings/HDX.yml
osm_export_tool/mappings/HDX_v2.yml
osm_export_tool/mappings/InAWARE.yml
osm_export_tool/mappings/default.yml
osm_export_tool/mappings/simple.yml
osm_export_tool-0.0.26.data/scripts/osm-export-tool
test/__init__.py
test/test_mapping.py
test/test_sources.py
test/test_sql.py
osm_export_tool-0.0.26.dist-info/LICENSE.md
osm_export_tool-0.0.26.dist-info/METADATA
osm_export_tool-0.0.26.dist-info/WHEEL
osm_export_tool-0.0.26.dist-info/top_level.txt
osm_export_tool-0.0.26.dist-info/RECORD
