Metadata-Version: 2.1
Name: osm-export-tool
Version: 0.0.26
Summary: Convert OpenStreetMap data into GIS and mobile mapping file formats.
Home-page: https://github.com/hotosm/osm-export-tool-python
Author: Brandon Liu
Author-email: brandon.liu@hotosm.org
License: BSD-3-Clause
Platform: UNKNOWN
Classifier: Programming Language :: Python :: 3
Classifier: License :: OSI Approved :: BSD License
Classifier: Operating System :: OS Independent
Requires-Dist: osmium (~=2.15)
Requires-Dist: pyparsing (~=2.4)
Requires-Dist: pyyaml
Requires-Dist: shapely (~=1.6)
Requires-Dist: requests (~=2.22.0)
Requires-Dist: landez (~=2.5.0)
